SpaMI/__init__.py
SpaMI/main.py
SpaMI/model.py
SpaMI/preprocess.py
SpaMI/utils.py
spami-1.0.0.dist-info/licenses/LICENSE
spami-1.0.0.dist-info/METADATA
spami-1.0.0.dist-info/WHEEL
spami-1.0.0.dist-info/top_level.txt
spami-1.0.0.dist-info/RECORD
