Metadata-Version: 2.4
Name: SpaMI
Version: 1.0.0
Summary: A spatial multi-omics data integration tool
Author: Gao congqiang
License: MIT License
Classifier: Development Status :: 3 - Alpha
Classifier: Intended Audience :: Developers
Classifier: License :: OSI Approved :: MIT License
Classifier: Programming Language :: Python :: 3
Classifier: Programming Language :: Python :: 3.8
Classifier: Programming Language :: Python :: 3.9
Classifier: Programming Language :: Python :: 3.10
Requires-Python: >=3.8
License-File: LICENSE
Requires-Dist: h5py>=3.10.0
Requires-Dist: scikit-learn>=1.3.2
Requires-Dist: episcanpy>=0.4.0
Requires-Dist: scipy>=1.10.1
Requires-Dist: numpy>=1.22.4
Requires-Dist: pandas>=2.0.3
Requires-Dist: scanpy>=1.9.8
Requires-Dist: anndata>=0.9.2
Requires-Dist: torch>=2.2.1
Requires-Dist: torch_geometric>=2.5.1
Requires-Dist: matplotlib>=3.7.5
Requires-Dist: tqdm>=4.66.2
Requires-Dist: POT>=0.9.3
Dynamic: license-file
